[
  {"title":"Développeur Frontend","company":"TechNova","location":"Paris","company_banner":"https://picsum.photos/id/1047/400/200","tags":"react,ui,js,tailwind"},
  {"title":"PM / Product Manager","company":"TechNova","location":"Paris","company_banner":"https://picsum.photos/id/1047/400/200","tags":"product,ux,analytics"},
  {"title":"Ingénieur Cloud","company":"GreenOps","location":"Lyon","company_banner":"https://picsum.photos/id/1039/400/200","tags":"k8s,cloud,finops,terraform"},
  {"title":"FinOps Engineer","company":"GreenOps","location":"Lyon","company_banner":"https://picsum.photos/id/1039/400/200","tags":"finops,k8s,cloud"},
  {"title":"Data Analyst","company":"DataPulse","location":"Nantes","company_banner":"https://picsum.photos/id/1033/400/200","tags":"sql,bi,python,tableau"},
  {"title":"BI Developer","company":"DataPulse","location":"Nantes","company_banner":"https://picsum.photos/id/1033/400/200","tags":"powerbi,dax,sql"},
  {"title":"Dev Fullstack","company":"WebForge","location":"Bordeaux","company_banner":"https://picsum.photos/id/1032/400/200","tags":"node,vue,fullstack,vitest"},
  {"title":"Tech Lead Front","company":"WebForge","location":"Bordeaux","company_banner":"https://picsum.photos/id/1032/400/200","tags":"react,webpack,testing"},
  {"title":"Pentester","company":"SecureMind","location":"Marseille","company_banner":"https://picsum.photos/id/1029/400/200","tags":"pentest,security,burp"},
  {"title":"AppSec Engineer","company":"SecureMind","location":"Marseille","company_banner":"https://picsum.photos/id/1029/400/200","tags":"appsec,devsecops"},
  {"title":"Product Designer","company":"NeoBank","location":"Paris","company_banner":"https://picsum.photos/id/1057/400/200","tags":"ux,ui,figma,accessibility"},
  {"title":"UX Writer","company":"NeoBank","location":"Paris","company_banner":"https://picsum.photos/id/1057/400/200","tags":"ux,content,writing"},
  {"title":"SRE / DevOps","company":"BlueCart","location":"Toulouse","company_banner":"https://picsum.photos/id/1050/400/200","tags":"sre,observability,terraform"},
  {"title":"Architecte Cloud","company":"BlueCart","location":"Toulouse","company_banner":"https://picsum.photos/id/1050/400/200","tags":"cloud,architecture,azure,gcp"},
  {"title":"Backend Java","company":"ByteWorks","location":"Grenoble","company_banner":"https://picsum.photos/id/1077/400/200","tags":"java,spring,sql"},
  {"title":"DataViz Engineer","company":"ByteWorks","location":"Grenoble","company_banner":"https://picsum.photos/id/1077/400/200","tags":"dataviz,d3js"},
  {"title":"Data Scientist","company":"HealthHub","location":"Rennes","company_banner":"https://picsum.photos/id/1064/400/200","tags":"ml,python,mlops"},
  {"title":"Fullstack TypeScript","company":"HealthHub","location":"Rennes","company_banner":"https://picsum.photos/id/1064/400/200","tags":"nextjs,nestjs,ts"},
  {"title":"QA Engineer","company":"AgriSoft","location":"Angers","company_banner":"https://picsum.photos/id/1067/400/200","tags":"qa,e2e,ci-cd"},
  {"title":"Chef de Projet IT","company":"AgriSoft","location":"Dijon","company_banner":"https://picsum.photos/id/1067/400/200","tags":"erp,crm,gestion"},
  {"title":"Go Backend Engineer","company":"OrbitMedia","location":"Clermont-Fd","company_banner":"https://picsum.photos/id/1070/400/200","tags":"go,grpc,kafka"},
  {"title":"Dev Mobile","company":"OrbitMedia","location":"Nice","company_banner":"https://picsum.photos/id/1070/400/200","tags":"flutter,mobile"},
  {"title":"Frontend Vue.js","company":"MobilityX","location":"Metz","company_banner":"https://picsum.photos/id/1060/400/200","tags":"vue,spa,typescript"},
  {"title":"Data Engineer","company":"MobilityX","location":"Lille","company_banner":"https://picsum.photos/id/1060/400/200","tags":"dataeng,airflow,dbt"}
]
